clement/__init__.py
clement/__main__.py
clement/base_controls.py
clement/em_operations.py
clement/fib_controls.py
clement/fm_controls.py
clement/fm_operations.py
clement/gis_controls.py
clement/gui.py
clement/peak_finding.py
clement/popup.py
clement/project.py
clement/ransac.py
clement/res_styles.py
clement/sem_controls.py
clement/tem_controls.py
clement/test_patterning.py
clement/utils.py
clement/styles/dark.qss
clement/styles/none.qss
clement/styles/solarized.qss
clement-0.3.0.dist-info/LICENSE
clement-0.3.0.dist-info/METADATA
clement-0.3.0.dist-info/WHEEL
clement-0.3.0.dist-info/entry_points.txt
clement-0.3.0.dist-info/top_level.txt
clement-0.3.0.dist-info/RECORD
