Metadata-Version: 2.1
Name: clement
Version: 0.3.0
Summary: GUI for Correlative Light and Electron Microscopy
Home-page: https://github.com/AyyerLab/Clement
Author: CNI Group at MPSD
Author-email: kartik.ayyer@mpsd.mpg.de
Classifier: Programming Language :: Python :: 3
Classifier: License :: OSI Approved :: GNU General Public License v3 (GPLv3)
Classifier: Development Status :: 3 - Alpha
Classifier: Topic :: Scientific/Engineering :: Visualization
Classifier: Operating System :: OS Independent
Classifier: Intended Audience :: Science/Research
Requires-Python: >=3.6
License-File: LICENSE
Requires-Dist: numpy
Requires-Dist: scipy >=1.0.0
Requires-Dist: scikit-image
Requires-Dist: scikit-learn
Requires-Dist: pyqt5
Requires-Dist: numexpr
Requires-Dist: mrcfile
Requires-Dist: read-lif ==0.4.0
Requires-Dist: tifffile
Requires-Dist: matplotlib
Requires-Dist: pyqtgraph
Requires-Dist: pyyaml
Requires-Dist: xmltodict
